jmbo_search-0.1.0.dist-info/DESCRIPTION.rst
jmbo_search-0.1.0.dist-info/METADATA
jmbo_search-0.1.0.dist-info/RECORD
jmbo_search-0.1.0.dist-info/WHEEL
jmbo_search-0.1.0.dist-info/metadata.json
jmbo_search-0.1.0.dist-info/top_level.txt
search/__init__.py
search/admin.py
search/base_search_indexes.py
search/models.py
search/signals.py
search/tasks.py
search/urls.py
search/views.py
search/fixtures/README.txt
search/fixtures/sites.json
search/management/__init__.py
search/management/commands/__init__.py
search/management/commands/get_last_foundry_migration.py
search/migrations/0001_initial.py
search/migrations/__init__.py
search/static/jmbo_search/README.txt
search/templates/jmbo_search/home.html
search/templates/search/search.html
search/templates/search/indexes/search/indexedmodelbase_text.txt
search/tests/__init__.py
search/tests/manage.py
search/tests/test_search.py
search/tests/urls.py
search/tests/requirements/19.txt
search/tests/res/image.jpg
search/tests/settings/19.py
search/tests/settings/__init__.py
